topically/__init__.py
topically/app.py
topically/cluster_namers.py
topically/prompts/prompts.py
topically/topic_namer.py
topically-0.0.5.dist-info/LICENSE
topically-0.0.5.dist-info/WHEEL
topically-0.0.5.dist-info/METADATA
topically-0.0.5.dist-info/RECORD
